revcolorsensor/__init__.py
revcolorsensor/colorsensor.py
revcolorsensor-1.0.5.dist-info/METADATA
revcolorsensor-1.0.5.dist-info/WHEEL
revcolorsensor-1.0.5.dist-info/RECORD
