Metadata-Version: 2.1
Name: revcolorsensor
Version: 1.0.5
Summary: This is a Python library that allows Raspberry Pi's to use the REV Color Sensor without a Roborio/FRC project.
Author: Jason Li
Author-email: jasonli.0616@outlook.com
Requires-Python: >=3.6,<4.0
Classifier: Programming Language :: Python :: 3
Classifier: Programming Language :: Python :: 3.6
Classifier: Programming Language :: Python :: 3.7
Classifier: Programming Language :: Python :: 3.8
Classifier: Programming Language :: Python :: 3.9
Classifier: Programming Language :: Python :: 3.10
Classifier: Programming Language :: Python :: 3.11
Classifier: Programming Language :: Python :: 3.12
Requires-Dist: pigpio (>=1.78,<2.0)
